mimeutil.py
mimeutil-1.0.4.dist-info/LICENSE
mimeutil-1.0.4.dist-info/METADATA
mimeutil-1.0.4.dist-info/WHEEL
mimeutil-1.0.4.dist-info/top_level.txt
mimeutil-1.0.4.dist-info/RECORD
